{"7:188":[{"t":"قُل لَّ","r":null},{"t":"آ","r":"madd_permissible"},{"t":" أَمْلِكُ لِنَفْسِى نَفْ","r":null},{"t":"عًا وَ","r":"ikhfa_idgham"},{"t":"لَا ضَرًّا إِلَّا مَا شَ","r":null},{"t":"آ","r":"madd_obligatory"},{"t":"ءَ ","r":null},{"t":"ٱ","r":"silent"},{"t":"للَّهُ وَلَوْ كُ","r":null},{"t":"نتُ","r":"ikhfa_idgham"},{"t":" أَعْلَمُ ","r":null},{"t":"ٱ","r":"silent"},{"t":"لْغَيْبَ لَ","r":null},{"t":"ٱ","r":"silent"},{"t":"سْتَكْثَرْتُ مِنَ ","r":null},{"t":"ٱ","r":"silent"},{"t":"لْخَيْرِ وَمَا مَسَّنِىَ ","r":null},{"t":"ٱل","r":"silent"},{"t":"سُّ","r":null},{"t":"وٓ","r":"madd_obligatory"},{"t":"ءُ إِنْ أَنَا۠ إِلَّا نَذِي","r":null},{"t":"رٌ وَ","r":"ikhfa_idgham"},{"t":"بَشِي","r":null},{"t":"رٌ لِّ","r":"ikhfa_idgham"},{"t":"قَوْ","r":null},{"t":"مٍ يُ","r":"ikhfa_idgham"},{"t":"ؤْمِنُ","r":null},{"t":"و","r":"madd_permissible"},{"t":"نَ","r":null}],"7:189":[{"t":"هُوَ ","r":null},{"t":"ٱ","r":"silent"},{"t":"لَّذِى خَلَقَكُ","r":null},{"t":"م مِّن نَّ","r":"ikhfa_idgham"},{"t":"فْ","r":null},{"t":"سٍ ","r":"ikhfa_idgham"},{"t":"وَٰ","r":"madd_permissible"},{"t":"حِدَ","r":null},{"t":"ةٍ وَ","r":"ikhfa_idgham"},{"t":"جَعَلَ مِنْهَا زَوْجَهَا لِيَسْكُنَ إِلَيْهَا فَلَ","r":null},{"t":"مَّ","r":"ghunnah"},{"t":"ا تَغَشَّ","r":null},{"t":"ىٰ","r":"madd_permissible"},{"t":"هَا حَمَلَتْ حَمْلًا خَفِي","r":null},{"t":"فًا فَ","r":"ikhfa_idgham"},{"t":"مَرَّتْ بِهِ","r":null},{"t":"ۦ","r":"madd_permissible"},{"t":" فَلَ","r":null},{"t":"مَّ","r":"ghunnah"},{"t":"آ","r":"madd_permissible"},{"t":" أَثْقَلَ","r":null},{"t":"ت","r":"ikhfa_idgham"},{"t":" دَّعَوَا ","r":null},{"t":"ٱ","r":"silent"},{"t":"للَّهَ رَبَّهُمَا لَئِنْ ءَاتَيْتَنَا ","r":null},{"t":"صَٰ","r":"madd_permissible"},{"t":"لِ","r":null},{"t":"حًا لَّ","r":"ikhfa_idgham"},{"t":"نَكُونَ","r":null},{"t":"نَّ","r":"ghunnah"},{"t":" مِنَ ","r":null},{"t":"ٱل","r":"silent"},{"t":"شَّٰ","r":"madd_permissible"},{"t":"كِرِ","r":null},{"t":"ي","r":"madd_permissible"},{"t":"نَ","r":null}],"7:190":[{"t":"فَلَ","r":null},{"t":"مَّ","r":"ghunnah"},{"t":"آ","r":"madd_permissible"},{"t":" ءَاتَ","r":null},{"t":"ىٰ","r":"madd_permissible"},{"t":"هُمَا ","r":null},{"t":"صَٰ","r":"madd_permissible"},{"t":"لِ","r":null},{"t":"حًا جَ","r":"ikhfa_idgham"},{"t":"عَلَا لَهُ","r":null},{"t":"ۥ","r":"madd_permissible"},{"t":" شُرَكَ","r":null},{"t":"آ","r":"madd_obligatory"},{"t":"ءَ فِيمَ","r":null},{"t":"آ","r":"madd_permissible"},{"t":" ءَاتَ","r":null},{"t":"ىٰ","r":"madd_permissible"},{"t":"هُمَا فَتَ","r":null},{"t":"عَٰ","r":"madd_permissible"},{"t":"لَى ","r":null},{"t":"ٱ","r":"silent"},{"t":"للَّهُ عَ","r":null},{"t":"مَّ","r":"ghunnah"},{"t":"ا يُشْرِكُ","r":null},{"t":"و","r":"madd_permissible"},{"t":"نَ","r":null}],"7:191":[{"t":"أَيُشْرِكُونَ مَا لَا يَخْلُقُ شَيْ","r":null},{"t":"ـًٔا وَ","r":"ikhfa_idgham"},{"t":"هُمْ يُخْلَقُ","r":null},{"t":"و","r":"madd_permissible"},{"t":"نَ","r":null}],"7:192":[{"t":"وَلَا يَسْتَطِيعُونَ لَهُمْ نَصْ","r":null},{"t":"رًا وَ","r":"ikhfa_idgham"},{"t":"لَ","r":null},{"t":"آ","r":"madd_permissible"},{"t":" أَ","r":null},{"t":"نفُ","r":"ikhfa_idgham"},{"t":"سَهُمْ يَ","r":null},{"t":"نصُ","r":"ikhfa_idgham"},{"t":"رُ","r":null},{"t":"و","r":"madd_permissible"},{"t":"نَ","r":null}],"7:193":[{"t":"وَإِ","r":null},{"t":"ن تَ","r":"ikhfa_idgham"},{"t":"دْ","r":"qalqalah"},{"t":"عُوهُمْ إِلَى ","r":null},{"t":"ٱ","r":"silent"},{"t":"لْهُدَىٰ لَا يَتَّبِعُوكُمْ سَوَ","r":null},{"t":"آ","r":"madd_obligatory"},{"t":"ءٌ عَلَيْكُمْ أَدَعَوْتُمُوهُمْ أَمْ أَ","r":null},{"t":"نتُ","r":"ikhfa_idgham"},{"t":"مْ ","r":null},{"t":"صَٰ","r":"madd_permissible"},{"t":"مِتُ","r":null},{"t":"و","r":"madd_permissible"},{"t":"نَ","r":null}],"7:194":[{"t":"إِ","r":null},{"t":"نَّ","r":"ghunnah"},{"t":" ","r":null},{"t":"ٱ","r":"silent"},{"t":"لَّذِينَ تَ","r":null},{"t":"دْ","r":"qalqalah"},{"t":"عُونَ مِ","r":null},{"t":"ن دُ","r":"ikhfa_idgham"},{"t":"ونِ ","r":null},{"t":"ٱ","r":"silent"},{"t":"للَّهِ عِبَادٌ أَمْثَالُكُمْ فَ","r":null},{"t":"ٱ","r":"silent"},{"t":"دْ","r":"qalqalah"},{"t":"عُوهُمْ فَلْيَسْتَجِيبُو","r":null},{"t":"ا۟","r":"silent"},{"t":" لَكُمْ إِ","r":null},{"t":"ن كُنتُ","r":"ikhfa_idgham"},{"t":"مْ ","r":null},{"t":"صَٰ","r":"madd_permissible"},{"t":"دِقِ","r":null},{"t":"ي","r":"madd_permissible"},{"t":"نَ","r":null}],"7:195":[{"t":"أَلَهُمْ أَرْجُ","r":null},{"t":"لٌ يَ","r":"ikhfa_idgham"},{"t":"مْشُونَ بِهَ","r":null},{"t":"آ","r":"madd_permissible"},{"t":" أَمْ لَهُمْ أَيْ","r":null},{"t":"دٍ يَ","r":"ikhfa_idgham"},{"t":"بْ","r":"qalqalah"},{"t":"طِشُونَ بِهَ","r":null},{"t":"آ","r":"madd_permissible"},{"t":" أَمْ لَهُمْ أَعْيُ","r":null},{"t":"نٌ يُ","r":"ikhfa_idgham"},{"t":"بْ","r":"qalqalah"},{"t":"صِرُونَ بِهَ","r":null},{"t":"آ","r":"madd_permissible"},{"t":" أَمْ لَهُمْ ءَاذَا","r":null},{"t":"نٌ يَ","r":"ikhfa_idgham"},{"t":"سْمَعُونَ بِهَا قُلِ ","r":null},{"t":"ٱ","r":"silent"},{"t":"دْ","r":"qalqalah"},{"t":"عُو","r":null},{"t":"ا۟","r":"silent"},{"t":" شُرَكَ","r":null},{"t":"آ","r":"madd_obligatory"},{"t":"ءَكُمْ ثُ","r":null},{"t":"مَّ","r":"ghunnah"},{"t":" كِيدُونِ فَلَا تُ","r":null},{"t":"نظِ","r":"ikhfa_idgham"},{"t":"رُ","r":null},{"t":"و","r":"madd_permissible"},{"t":"نِ","r":null}]}