{"26:20":[{"t":"قَالَ فَعَلْتُهَ","r":null},{"t":"آ","r":"madd_permissible"},{"t":" إِ","r":null},{"t":"ذًا وَ","r":"ikhfa_idgham"},{"t":"أَنَا۠ مِنَ ","r":null},{"t":"ٱل","r":"silent"},{"t":"ضَّ","r":null},{"t":"آ","r":"madd_obligatory"},{"t":"لِّ","r":null},{"t":"ي","r":"madd_permissible"},{"t":"نَ","r":null}],"26:21":[{"t":"فَفَرَرْتُ مِ","r":null},{"t":"نكُ","r":"ikhfa_idgham"},{"t":"مْ لَ","r":null},{"t":"مَّ","r":"ghunnah"},{"t":"ا خِفْتُكُمْ فَوَهَبَ لِى رَبِّى حُكْ","r":null},{"t":"مًا وَ","r":"ikhfa_idgham"},{"t":"جَعَلَنِى مِنَ ","r":null},{"t":"ٱ","r":"silent"},{"t":"لْمُرْسَلِ","r":null},{"t":"ي","r":"madd_permissible"},{"t":"نَ","r":null}],"26:22":[{"t":"وَتِلْكَ نِعْمَ","r":null},{"t":"ةٌ تَ","r":"ikhfa_idgham"},{"t":"مُ","r":null},{"t":"نُّ","r":"ghunnah"},{"t":"هَا عَلَىَّ أَنْ عَبَّ","r":null},{"t":"د","r":"ikhfa_idgham"},{"t":"تَّ بَنِ","r":null},{"t":"ىٓ","r":"madd_permissible"},{"t":" إِسْ","r":null},{"t":"رَٰٓ","r":"madd_obligatory"},{"t":"ءِ","r":null},{"t":"ي","r":"madd_permissible"},{"t":"لَ","r":null}],"26:23":[{"t":"قَالَ فِرْعَوْنُ وَمَا رَبُّ ","r":null},{"t":"ٱ","r":"silent"},{"t":"لْ","r":null},{"t":"عَٰ","r":"madd_permissible"},{"t":"لَمِ","r":null},{"t":"ي","r":"madd_permissible"},{"t":"نَ","r":null}],"26:24":[{"t":"قَالَ رَبُّ ","r":null},{"t":"ٱل","r":"silent"},{"t":"سَّ","r":null},{"t":"مَٰوَٰ","r":"madd_permissible"},{"t":"تِ وَ","r":null},{"t":"ٱ","r":"silent"},{"t":"لْأَرْضِ وَمَا بَيْنَهُمَ","r":null},{"t":"آ","r":"madd_permissible"},{"t":" إِ","r":null},{"t":"ن كُنتُم مُّ","r":"ikhfa_idgham"},{"t":"وقِنِ","r":null},{"t":"ي","r":"madd_permissible"},{"t":"نَ","r":null}],"26:25":[{"t":"قَالَ لِمَنْ حَوْلَهُ","r":null},{"t":"ۥٓ","r":"madd_permissible"},{"t":" أَلَا تَسْتَمِعُ","r":null},{"t":"و","r":"madd_permissible"},{"t":"نَ","r":null}],"26:26":[{"t":"قَالَ رَبُّكُمْ وَرَبُّ ءَابَ","r":null},{"t":"آ","r":"madd_obligatory"},{"t":"ئِكُمُ ","r":null},{"t":"ٱ","r":"silent"},{"t":"لْأَوَّلِ","r":null},{"t":"ي","r":"madd_permissible"},{"t":"نَ","r":null}],"26:27":[{"t":"قَالَ إِ","r":null},{"t":"نَّ","r":"ghunnah"},{"t":" رَسُولَكُمُ ","r":null},{"t":"ٱ","r":"silent"},{"t":"لَّذِ","r":null},{"t":"ىٓ","r":"madd_permissible"},{"t":" أُرْسِلَ إِلَيْكُمْ لَمَ","r":null},{"t":"جْ","r":"qalqalah"},{"t":"نُ","r":null},{"t":"و","r":"madd_permissible"},{"t":"نٌ","r":null}],"26:28":[{"t":"قَالَ رَبُّ ","r":null},{"t":"ٱ","r":"silent"},{"t":"لْمَشْرِقِ وَ","r":null},{"t":"ٱ","r":"silent"},{"t":"لْمَغْرِبِ وَمَا بَيْنَهُمَ","r":null},{"t":"آ","r":"madd_permissible"},{"t":" إِ","r":null},{"t":"ن كُنتُ","r":"ikhfa_idgham"},{"t":"مْ تَعْقِلُ","r":null},{"t":"و","r":"madd_permissible"},{"t":"نَ","r":null}],"26:29":[{"t":"قَالَ لَئِنِ ","r":null},{"t":"ٱ","r":"silent"},{"t":"تَّخَذْتَ إِ","r":null},{"t":"لَٰ","r":"madd_permissible"},{"t":"هًا غَيْرِى لَأَ","r":null},{"t":"جْ","r":"qalqalah"},{"t":"عَلَ","r":null},{"t":"نَّ","r":"ghunnah"},{"t":"كَ مِنَ ","r":null},{"t":"ٱ","r":"silent"},{"t":"لْمَسْجُونِ","r":null},{"t":"ي","r":"madd_permissible"},{"t":"نَ","r":null}],"26:30":[{"t":"قَالَ أَوَلَوْ جِئْتُكَ بِشَىْ","r":null},{"t":"ءٍ مُّ","r":"ikhfa_idgham"},{"t":"بِ","r":null},{"t":"ي","r":"madd_permissible"},{"t":"نٍ","r":null}],"26:31":[{"t":"قَالَ فَأْتِ بِهِ","r":null},{"t":"ۦٓ","r":"madd_permissible"},{"t":" إِ","r":null},{"t":"ن كُنتَ","r":"ikhfa_idgham"},{"t":" مِنَ ","r":null},{"t":"ٱل","r":"silent"},{"t":"صَّٰ","r":"madd_permissible"},{"t":"دِقِ","r":null},{"t":"ي","r":"madd_permissible"},{"t":"نَ","r":null}],"26:32":[{"t":"فَأَلْقَىٰ عَصَاهُ فَإِذَا هِىَ ثُعْبَا","r":null},{"t":"نٌ مُّ","r":"ikhfa_idgham"},{"t":"بِ","r":null},{"t":"ي","r":"madd_permissible"},{"t":"نٌ","r":null}],"26:33":[{"t":"وَنَزَعَ يَدَهُ","r":null},{"t":"ۥ","r":"madd_permissible"},{"t":" فَإِذَا هِىَ بَيْضَ","r":null},{"t":"آ","r":"madd_obligatory"},{"t":"ءُ لِ","r":null},{"t":"ل","r":"silent"},{"t":"نَّٰ","r":"madd_permissible"},{"t":"ظِرِ","r":null},{"t":"ي","r":"madd_permissible"},{"t":"نَ","r":null}],"26:34":[{"t":"قَالَ لِلْمَلَإِ حَوْلَهُ","r":null},{"t":"ۥٓ","r":"madd_permissible"},{"t":" إِ","r":null},{"t":"نَّ","r":"ghunnah"},{"t":" ","r":null},{"t":"هَٰ","r":"madd_permissible"},{"t":"ذَا لَ","r":null},{"t":"سَٰ","r":"madd_permissible"},{"t":"حِرٌ عَلِ","r":null},{"t":"ي","r":"madd_permissible"},{"t":"مٌ","r":null}],"26:35":[{"t":"يُرِيدُ أَ","r":null},{"t":"ن يُ","r":"ikhfa_idgham"},{"t":"خْرِجَكُ","r":null},{"t":"م مِّ","r":"ikhfa_idgham"},{"t":"نْ أَرْضِكُ","r":null},{"t":"م بِ","r":"ikhfa_idgham"},{"t":"سِحْرِهِ","r":null},{"t":"ۦ","r":"madd_permissible"},{"t":" فَمَاذَا تَأْمُرُ","r":null},{"t":"و","r":"madd_permissible"},{"t":"نَ","r":null}],"26:36":[{"t":"قَالُ","r":null},{"t":"وٓ","r":"madd_permissible"},{"t":"ا۟","r":"silent"},{"t":" أَرْجِهْ وَأَخَاهُ وَ","r":null},{"t":"ٱ","r":"silent"},{"t":"بْ","r":"qalqalah"},{"t":"عَثْ فِى ","r":null},{"t":"ٱ","r":"silent"},{"t":"لْمَدَ","r":null},{"t":"آ","r":"madd_obligatory"},{"t":"ئِنِ ","r":null},{"t":"حَٰ","r":"madd_permissible"},{"t":"شِرِ","r":null},{"t":"ي","r":"madd_permissible"},{"t":"نَ","r":null}],"26:37":[{"t":"يَأْتُوكَ بِكُلِّ سَحَّارٍ عَلِ","r":null},{"t":"ي","r":"madd_permissible"},{"t":"مٍ","r":null}],"26:38":[{"t":"فَجُمِعَ ","r":null},{"t":"ٱل","r":"silent"},{"t":"سَّحَرَةُ لِمِي","r":null},{"t":"قَٰ","r":"madd_permissible"},{"t":"تِ يَوْ","r":null},{"t":"مٍ مَّ","r":"ikhfa_idgham"},{"t":"عْلُ","r":null},{"t":"و","r":"madd_permissible"},{"t":"مٍ","r":null}],"26:39":[{"t":"وَقِيلَ لِ","r":null},{"t":"ل","r":"silent"},{"t":"نَّ","r":"ghunnah"},{"t":"اسِ هَلْ أَ","r":null},{"t":"نتُم مُّ","r":"ikhfa_idgham"},{"t":"جْ","r":"qalqalah"},{"t":"تَمِعُ","r":null},{"t":"و","r":"madd_permissible"},{"t":"نَ","r":null}]}