{"38:84":[{"t":"قَالَ فَ","r":null},{"t":"ٱ","r":"silent"},{"t":"لْحَقُّ وَ","r":null},{"t":"ٱ","r":"silent"},{"t":"لْحَقَّ أَقُ","r":null},{"t":"و","r":"madd_permissible"},{"t":"لُ","r":null}],"38:85":[{"t":"لَأَمْلَأَ","r":null},{"t":"نَّ","r":"ghunnah"},{"t":" جَهَ","r":null},{"t":"نَّ","r":"ghunnah"},{"t":"مَ مِ","r":null},{"t":"نكَ","r":"ikhfa_idgham"},{"t":" وَمِ","r":null},{"t":"مَّ","r":"ghunnah"},{"t":"ن تَ","r":"ikhfa_idgham"},{"t":"بِعَكَ مِنْهُمْ أَ","r":null},{"t":"جْ","r":"qalqalah"},{"t":"مَعِ","r":null},{"t":"ي","r":"madd_permissible"},{"t":"نَ","r":null}],"38:86":[{"t":"قُلْ مَ","r":null},{"t":"آ","r":"madd_permissible"},{"t":" أَسْـَٔلُكُمْ عَلَيْهِ مِنْ أَ","r":null},{"t":"جْ","r":"qalqalah"},{"t":"رٍ وَ","r":"ikhfa_idgham"},{"t":"مَ","r":null},{"t":"آ","r":"madd_permissible"},{"t":" أَنَا۠ مِنَ ","r":null},{"t":"ٱ","r":"silent"},{"t":"لْمُتَكَلِّفِ","r":null},{"t":"ي","r":"madd_permissible"},{"t":"نَ","r":null}],"38:87":[{"t":"إِنْ هُوَ إِلَّا ذِكْ","r":null},{"t":"رٌ لِّ","r":"ikhfa_idgham"},{"t":"لْ","r":null},{"t":"عَٰ","r":"madd_permissible"},{"t":"لَمِ","r":null},{"t":"ي","r":"madd_permissible"},{"t":"نَ","r":null}],"38:88":[{"t":"وَلَتَعْلَمُ","r":null},{"t":"نَّ","r":"ghunnah"},{"t":" نَبَأَهُ","r":null},{"t":"ۥ","r":"madd_permissible"},{"t":" بَعْدَ حِ","r":null},{"t":"ي","r":"madd_permissible"},{"t":"نٍۭ","r":null}],"39:1":[{"t":"تَ","r":null},{"t":"نزِ","r":"ikhfa_idgham"},{"t":"يلُ ","r":null},{"t":"ٱ","r":"silent"},{"t":"لْكِ","r":null},{"t":"تَٰ","r":"madd_permissible"},{"t":"بِ مِنَ ","r":null},{"t":"ٱ","r":"silent"},{"t":"للَّهِ ","r":null},{"t":"ٱ","r":"silent"},{"t":"لْعَزِيزِ ","r":null},{"t":"ٱ","r":"silent"},{"t":"لْحَكِ","r":null},{"t":"ي","r":"madd_permissible"},{"t":"مِ","r":null}],"39:2":[{"t":"إِ","r":null},{"t":"نَّ","r":"ghunnah"},{"t":"آ","r":"madd_permissible"},{"t":" أَ","r":null},{"t":"نزَ","r":"ikhfa_idgham"},{"t":"لْنَ","r":null},{"t":"آ","r":"madd_permissible"},{"t":" إِلَيْكَ ","r":null},{"t":"ٱ","r":"silent"},{"t":"لْكِ","r":null},{"t":"تَٰ","r":"madd_permissible"},{"t":"بَ بِ","r":null},{"t":"ٱ","r":"silent"},{"t":"لْحَقِّ فَ","r":null},{"t":"ٱ","r":"silent"},{"t":"عْبُدِ ","r":null},{"t":"ٱ","r":"silent"},{"t":"للَّهَ مُخْلِ","r":null},{"t":"صًا لَّ","r":"ikhfa_idgham"},{"t":"هُ ","r":null},{"t":"ٱل","r":"silent"},{"t":"دِّ","r":null},{"t":"ي","r":"madd_permissible"},{"t":"نَ","r":null}],"39:3":[{"t":"أَلَا لِلَّهِ ","r":null},{"t":"ٱل","r":"silent"},{"t":"دِّينُ ","r":null},{"t":"ٱ","r":"silent"},{"t":"لْخَالِصُ وَ","r":null},{"t":"ٱ","r":"silent"},{"t":"لَّذِينَ ","r":null},{"t":"ٱ","r":"silent"},{"t":"تَّخَذُو","r":null},{"t":"ا۟","r":"silent"},{"t":" مِ","r":null},{"t":"ن دُ","r":"ikhfa_idgham"},{"t":"ونِهِ","r":null},{"t":"ۦٓ","r":"madd_permissible"},{"t":" أَوْلِيَ","r":null},{"t":"آ","r":"madd_obligatory"},{"t":"ءَ مَا نَعْبُدُهُمْ إِلَّا لِيُقَرِّبُونَ","r":null},{"t":"آ","r":"madd_permissible"},{"t":" إِلَى ","r":null},{"t":"ٱ","r":"silent"},{"t":"للَّهِ زُلْفَ","r":null},{"t":"ىٰٓ","r":"madd_permissible"},{"t":" إِ","r":null},{"t":"نَّ","r":"ghunnah"},{"t":" ","r":null},{"t":"ٱ","r":"silent"},{"t":"للَّهَ يَحْكُمُ بَيْنَهُمْ فِى مَا هُمْ فِيهِ يَخْتَلِفُونَ إِ","r":null},{"t":"نَّ","r":"ghunnah"},{"t":" ","r":null},{"t":"ٱ","r":"silent"},{"t":"للَّهَ لَا يَهْدِى مَنْ هُوَ ","r":null},{"t":"كَٰ","r":"madd_permissible"},{"t":"ذِ","r":null},{"t":"بٌ كَ","r":"ikhfa_idgham"},{"t":"فَّ","r":null},{"t":"ا","r":"madd_permissible"},{"t":"رٌ","r":null}],"39:4":[{"t":"لَّوْ أَرَادَ ","r":null},{"t":"ٱ","r":"silent"},{"t":"للَّهُ أَ","r":null},{"t":"ن يَ","r":"ikhfa_idgham"},{"t":"تَّخِذَ وَلَ","r":null},{"t":"دًا لَّ","r":"ikhfa_idgham"},{"t":"ٱ","r":"silent"},{"t":"صْطَفَىٰ مِ","r":null},{"t":"مَّ","r":"ghunnah"},{"t":"ا يَخْلُقُ مَا يَشَ","r":null},{"t":"آ","r":"madd_obligatory"},{"t":"ءُ سُ","r":null},{"t":"بْ","r":"qalqalah"},{"t":"حَٰ","r":"madd_permissible"},{"t":"نَهُ","r":null},{"t":"ۥ","r":"madd_permissible"},{"t":" هُوَ ","r":null},{"t":"ٱ","r":"silent"},{"t":"للَّهُ ","r":null},{"t":"ٱ","r":"silent"},{"t":"لْ","r":null},{"t":"وَٰ","r":"madd_permissible"},{"t":"حِدُ ","r":null},{"t":"ٱ","r":"silent"},{"t":"لْقَهَّ","r":null},{"t":"ا","r":"madd_permissible"},{"t":"رُ","r":null}],"39:5":[{"t":"خَلَقَ ","r":null},{"t":"ٱل","r":"silent"},{"t":"سَّ","r":null},{"t":"مَٰوَٰ","r":"madd_permissible"},{"t":"تِ وَ","r":null},{"t":"ٱ","r":"silent"},{"t":"لْأَرْضَ بِ","r":null},{"t":"ٱ","r":"silent"},{"t":"لْحَقِّ يُكَوِّرُ ","r":null},{"t":"ٱ","r":"silent"},{"t":"لَّيْلَ عَلَى ","r":null},{"t":"ٱل","r":"silent"},{"t":"نَّ","r":"ghunnah"},{"t":"هَارِ وَيُكَوِّرُ ","r":null},{"t":"ٱل","r":"silent"},{"t":"نَّ","r":"ghunnah"},{"t":"هَارَ عَلَى ","r":null},{"t":"ٱ","r":"silent"},{"t":"لَّيْلِ وَسَخَّرَ ","r":null},{"t":"ٱل","r":"silent"},{"t":"شَّمْسَ وَ","r":null},{"t":"ٱ","r":"silent"},{"t":"لْقَمَرَ كُ","r":null},{"t":"لٌّ يَ","r":"ikhfa_idgham"},{"t":"جْ","r":"qalqalah"},{"t":"رِى لِأَجَ","r":null},{"t":"لٍ مُّ","r":"ikhfa_idgham"},{"t":"سَ","r":null},{"t":"مًّ","r":"ghunnah"},{"t":"ى أَلَا هُوَ ","r":null},{"t":"ٱ","r":"silent"},{"t":"لْعَزِيزُ ","r":null},{"t":"ٱ","r":"silent"},{"t":"لْغَ","r":null},{"t":"فَّٰ","r":"madd_permissible"},{"t":"رُ","r":null}]}